CHANGES.txt
MANIFEST.in
README.md
setup.py
avro_service_clients/__init__.py
avro_service_clients/constants.py
avro_service_clients/core.py
avro_service_clients/interfaces.py
avro_service_clients/utils.py
avro_service_clients/version.py
avro_service_clients.egg-info/PKG-INFO
avro_service_clients.egg-info/SOURCES.txt
avro_service_clients.egg-info/dependency_links.txt
avro_service_clients.egg-info/requires.txt
avro_service_clients.egg-info/top_level.txt
avro_service_clients/loaders/__init__.py
avro_service_clients/loaders/environment.py
avro_service_clients/protocols/__init__.py
avro_service_clients/protocols/local.py
requirements/core.txt
requirements/test.txt
tests/test_loaders/__init__.py
tests/test_loaders/test_environment.py
tests/test_protocols/__init__.py
tests/test_protocols/test_local.py