Metadata-Version: 1.1
Name: avro-service-clients
Version: 0.0.4
Summary: avro-service-clients
Home-page: https://github.com/packagelib/avro-service-clients
Author: Alex Milstead
Author-email: alex@amilstead.com
License: Apache License (2.0)
Platform: UNKNOWN
Classifier: Programming Language :: Python
Classifier: Development Status :: 3 - Alpha
Classifier: License :: OSI Approved :: Apache Software License
